<?xml version="1.0" standalone="yes"?>
<dsShedule xmlns="http://tempuri.org/dsEducLoad.xsd">
  <Group>
    <Id>-3</Id>
    <Name>ИВТ-461</Name>
  </Group>
  <Group>
    <Id>-4</Id>
    <Name>ИВТ-462</Name>
  </Group>
  <Group>
    <Id>2</Id>
    <Name>ИВТ-463</Name>
  </Group>
  <Group>
    <Id>3</Id>
    <Name>ИВТ-464</Name>
  </Group>
  <Group>
    <Id>4</Id>
    <Name>ИВТ-465</Name>
  </Group>
  <Group>
    <Id>5</Id>
    <Name>ИВТ-460</Name>
  </Group>
  <Group>
    <Id>7</Id>
    <Name>ИВТ-360</Name>
  </Group>
  <Group>
    <Id>8</Id>
    <Name>ИВТ-361</Name>
  </Group>
  <Group>
    <Id>9</Id>
    <Name>ИВТ-362</Name>
  </Group>
  <Group>
    <Id>10</Id>
    <Name>ИВТ-363</Name>
  </Group>
  <Group>
    <Id>11</Id>
    <Name>ИВТ-364</Name>
  </Group>
  <Group>
    <Id>12</Id>
    <Name>ИВТ-365</Name>
  </Group>
  <Group>
    <Id>13</Id>
    <Name>ЭВМ-5</Name>
  </Group>
  <Group>
    <Id>14</Id>
    <Name>ЭВМ-5.1п</Name>
  </Group>
  <Group>
    <Id>15</Id>
    <Name>ЭВМ-5.2п</Name>
  </Group>
  <Group>
    <Id>16</Id>
    <Name>ВТ-560</Name>
  </Group>
</dsShedule>